elixir_client/__init__.py
elixir_client/config.py
elixir_client/core.py
elixir_client/decorators.py
elixir_client/dn_tracer.py
elixir_client/file_uploader.py
elixir_client/output/__init__.py
elixir_client/output/results_handler.py
elixir_client/utils/__init__.py
elixir_client/utils/audio_utils.py
elixir_client/utils/file_type_classifier.py
runes_client/__init__.py
runes_client/api_client.py
runes_client/config.py
runes_client/core.py
runes_client/decorators.py
runes_client/dn_tracer.py
runes_client/file_uploader.py
runes_client/output/__init__.py
runes_client/output/results_handler.py
runes_client/utils/__init__.py
runes_client/utils/audio_utils.py
runes_client/utils/file_type_classifier.py
tests/__init__.py
tests/test_audio_utils.py
tests/test_core.py
tests/test_registration.py
tests/test_results_handler.py
runes_client-0.9.4.dist-info/LICENSE.md
runes_client-0.9.4.dist-info/METADATA
runes_client-0.9.4.dist-info/WHEEL
runes_client-0.9.4.dist-info/entry_points.txt
runes_client-0.9.4.dist-info/top_level.txt
runes_client-0.9.4.dist-info/RECORD
